{
    "Ar36": {
        "error": 0.0003507265081770695, 
        "filter_outliers_dict": {
            "filter_outliers": true, 
            "iterations": 1, 
            "std_devs": 2
        }, 
        "fit": "Linear", 
        "value": 0.01675165816339526
    }, 
    "Ar37": {
        "error": 0.012002266015705245, 
        "filter_outliers_dict": {
            "filter_outliers": true, 
            "iterations": 1, 
            "std_devs": 2
        }, 
        "fit": "linear", 
        "value": 10.871645258849037
    }, 
    "Ar38": {
        "error": 0.004330327369466851, 
        "filter_outliers_dict": {
            "filter_outliers": true, 
            "iterations": 1, 
            "std_devs": 2
        }, 
        "fit": "linear", 
        "value": 0.6589051471738723
    }, 
    "Ar39": {
        "error": 0.0173339849539284, 
        "filter_outliers_dict": {
            "filter_outliers": true, 
            "iterations": 1, 
            "std_devs": 2
        }, 
        "fit": "Linear", 
        "value": 52.00374478227944
    }, 
    "Ar40": {
        "error": 0.025863640344534183, 
        "filter_outliers_dict": {
            "filter_outliers": true, 
            "iterations": 1, 
            "std_devs": 2
        }, 
        "fit": "Linear", 
        "value": 232.55872674972593
    }, 
    "Ar41": {
        "error": 0.0032884020247716814, 
        "filter_outliers_dict": {
            "filter_outliers": true, 
            "iterations": 1, 
            "std_devs": 2
        }, 
        "fit": "Average", 
        "value": -0.06577779438186118
    }
}