{
    "Ar36": {
        "error": 0.0003324790909118235,
        "filter_outliers_dict": {
            "filter_outliers": true,
            "iterations": 1,
            "std_devs": 2
        },
        "fit": "Parabolic",
        "fn": 381,
        "include_baseline_error": false,
        "n": 400,
        "reviewed": true,
        "value": 0.018380421939098633
    },
    "Ar37": {
        "error": 0.012181527757988524,
        "filter_outliers_dict": {
            "filter_outliers": true,
            "iterations": 1,
            "std_devs": 2
        },
        "fit": "Linear",
        "fn": 381,
        "include_baseline_error": false,
        "n": 400,
        "reviewed": true,
        "value": 4.457736246868099
    },
    "Ar38": {
        "error": 0.01377685245187448,
        "filter_outliers_dict": {
            "filter_outliers": true,
            "iterations": 1,
            "std_devs": 2
        },
        "fit": "Linear",
        "fn": 382,
        "include_baseline_error": false,
        "n": 400,
        "reviewed": true,
        "value": 0.1436067933600958
    },
    "Ar39": {
        "error": 0.02527104183120679,
        "filter_outliers_dict": {
            "filter_outliers": true,
            "iterations": 1,
            "std_devs": 2
        },
        "fit": "Parabolic",
        "fn": 387,
        "include_baseline_error": false,
        "n": 400,
        "reviewed": true,
        "value": 19.69706787695168
    },
    "Ar40": {
        "error": 0.02967349486646848,
        "filter_outliers_dict": {
            "filter_outliers": true,
            "iterations": 1,
            "std_devs": 2
        },
        "fit": "Parabolic",
        "fn": 384,
        "include_baseline_error": false,
        "n": 400,
        "reviewed": true,
        "value": 145.02202171066426
    },
    "reviewed": true
}